wos_parser/__init__.py
wos_parser/constants.py
wos_parser/wos_parser.py
wos_parser/elements/__init__.py
wos_parser/elements/addressname.py
wos_parser/elements/addressspec.py
wos_parser/elements/bibpagecount.py
wos_parser/elements/categoryinfo.py
wos_parser/elements/fundack.py
wos_parser/elements/grant.py
wos_parser/elements/identifier.py
wos_parser/elements/ids.py
wos_parser/elements/language.py
wos_parser/elements/name.py
wos_parser/elements/oases.py
wos_parser/elements/organization.py
wos_parser/elements/page.py
wos_parser/elements/physicalsection.py
wos_parser/elements/pubinfo.py
wos_parser/elements/publisher.py
wos_parser/elements/reference.py
wos_parser/elements/subject.py
wos_parser/elements/title.py
wos_parser/records/__init__.py
wos_parser/records/fullrecordmetadata.py
wos_parser/records/item.py
wos_parser/records/record.py
wos_parser/records/summary.py
wos_parser-0.1.0.dist-info/LICENSE
wos_parser-0.1.0.dist-info/METADATA
wos_parser-0.1.0.dist-info/WHEEL
wos_parser-0.1.0.dist-info/top_level.txt
wos_parser-0.1.0.dist-info/RECORD
