Metadata-Version: 2.1
Name: wos_parser
Version: 0.1.0
Summary: A parser for Web of Science XML data in Python.
Author-email: Simon Stone <simon.stone@dartmouth.edu>
Maintainer-email: Simon Stone <simon.stone@dartmouth.edu>
License: MIT license
Project-URL: bugs, https://git.dartmouth.edu/lib-digital-strategies/RDS/projects/web-of-science-xml-parser/issues
Project-URL: homepage, https://git.dartmouth.edu/lib-digital-strategies/RDS/projects/web-of-science-xml-parser
Requires-Python: >=3.8
License-File: LICENSE
Requires-Dist: tqdm
